atomfoxapi/__init__.py
atomfoxapi/main.py
atomfoxapi/test.py
atomfoxapi-1.3.1.dist-info/METADATA
atomfoxapi-1.3.1.dist-info/WHEEL
atomfoxapi-1.3.1.dist-info/top_level.txt
atomfoxapi-1.3.1.dist-info/RECORD
